autowx_sdk/__init__.py
autowx_sdk/autowx_sdk.py
autowx_sdk/crypto.py
autowx_sdk/im.py
autowx_sdk/request.py
autowx_sdk/sign.py
autowx_sdk-0.1.1.dist-info/METADATA
autowx_sdk-0.1.1.dist-info/WHEEL
autowx_sdk-0.1.1.dist-info/top_level.txt
autowx_sdk-0.1.1.dist-info/RECORD
