Metadata-Version: 2.1
Name: autowx_sdk
Version: 0.1.1
Summary: my package
